malduck/__init__.py
malduck/bits.py
malduck/disasm.py
malduck/dnpe.py
malduck/ints.py
malduck/main.py
malduck/pe.py
malduck/py.typed
malduck/structure.py
malduck/verify.py
malduck/yara.py
malduck/yara.pyi
malduck/compression/__init__.py
malduck/compression/aplib.py
malduck/compression/gzip.py
malduck/compression/lznt1.py
malduck/compression/components/__init__.py
malduck/compression/components/aplib.py
malduck/compression/components/lznt1.py
malduck/crypto/__init__.py
malduck/crypto/aes.py
malduck/crypto/blowfish.py
malduck/crypto/camellia.py
malduck/crypto/chacha20.py
malduck/crypto/des3.py
malduck/crypto/rabbit.py
malduck/crypto/rc.py
malduck/crypto/rsa.py
malduck/crypto/salsa20.py
malduck/crypto/serpent.py
malduck/crypto/winhdr.py
malduck/crypto/xor.py
malduck/crypto/components/__init__.py
malduck/crypto/components/pyserpent.py
malduck/extractor/__init__.py
malduck/extractor/config_utils.py
malduck/extractor/extract_manager.py
malduck/extractor/extractor.py
malduck/extractor/extractor.pyi
malduck/extractor/modules.py
malduck/hash/__init__.py
malduck/hash/crc.py
malduck/hash/sha.py
malduck/procmem/__init__.py
malduck/procmem/binmem.py
malduck/procmem/cuckoomem.py
malduck/procmem/idamem.py
malduck/procmem/procmem.py
malduck/procmem/procmem.pyi
malduck/procmem/procmemdnpe.py
malduck/procmem/procmemelf.py
malduck/procmem/procmempe.py
malduck/procmem/region.py
malduck/string/__init__.py
malduck/string/bin.py
malduck/string/inet.py
malduck/string/ops.py
malduck-4.4.1.dist-info/LICENSE
malduck-4.4.1.dist-info/METADATA
malduck-4.4.1.dist-info/WHEEL
malduck-4.4.1.dist-info/entry_points.txt
malduck-4.4.1.dist-info/top_level.txt
malduck-4.4.1.dist-info/RECORD
