Metadata-Version: 2.1
Name: malduck
Version: 4.4.1
Summary: Malduck is your ducky companion in malware analysis journeys
Home-page: https://github.com/CERT-Polska/malduck
Author: CERT Polska
Author-email: info@cert.pl
License: GPLv3
Platform: UNKNOWN
Classifier: Programming Language :: Python :: 3
Classifier: Operating System :: POSIX :: Linux
Requires-Python: >=3.8
License-File: LICENSE
Requires-Dist: capstone (>=4.0.1)
Requires-Dist: click (>=7.0)
Requires-Dist: cryptography (>=3.1)
Requires-Dist: dnfile (>=0.15.0)
Requires-Dist: pefile (>=2022.5.30)
Requires-Dist: pycryptodomex (>=3.8.2)
Requires-Dist: pyelftools
Requires-Dist: typing-extensions (>=3.7.4.2)
Requires-Dist: yara-python
